betacode_parser/__init__.py
betacode_parser/coptic_lists.py
betacode_parser/coptic_parser.py
betacode_parser/greek_lists.py
betacode_parser/greek_parser.py
betacode_parser/hebrew_lists.py
betacode_parser/hebrew_parser.py
betacode_parser/parser.py
betacode_parser-1.0.1.dist-info/licenses/LICENSE
betacode_parser-1.0.1.dist-info/METADATA
betacode_parser-1.0.1.dist-info/WHEEL
betacode_parser-1.0.1.dist-info/top_level.txt
betacode_parser-1.0.1.dist-info/RECORD
