Metadata-Version: 2.4
Name: betacode-parser
Version: 1.0.1
Summary: A fully implemented Beta Code parser.
Author: Ved Rane
License-Expression: MIT
Project-URL: Homepage, https://github.com/vedrane/betacode-parser
Project-URL: Issues, https://github.com/vedrane/betacode-parser/issues
Classifier: Programming Language :: Python :: 3
Classifier: Operating System :: OS Independent
Requires-Python: >=3.8
License-File: LICENSE
Dynamic: license-file
